vt/__init__.py
az_vt-0.0.1.dist-info/WHEEL
az_vt-0.0.1.dist-info/METADATA
az_vt-0.0.1.dist-info/RECORD
