Metadata-Version: 2.1
Name: az-vt
Version: 0.0.1
Summary: az-vt
Author: Stefano Borini
Requires-Python: >=3.7,<4.0
Classifier: Programming Language :: Python :: 3
Classifier: Programming Language :: Python :: 3.7
Classifier: Programming Language :: Python :: 3.8
